{
  "sightings": [
    {
      "id": "lpr1_treugolnik/240123:Орловская область",
      "location": "Орловская область",
      "locationRu": "Орловская область",
      "region": "Орловская область",
      "lat": 52.4316213,
      "lon": 35.6043309,
      "geocodeSource": "nominatim",
      "geocodePrecision": "point",
      "matchedName": "Орловская область",
      "threatType": "drone",
      "count": null,
      "heading": null,
      "destination": null,
      "destinationLat": null,
      "destinationLon": null,
      "bearing": null,
      "status": "alert",
      "confidence": 0.55,
      "postId": 240123,
      "postLink": "https://t.me/lpr1_treugolnik/240123",
      "postText": "Орловская область\n\nТревога по БПЛА от Курской области",
      "postDate": "2026-07-07T16:40:33+00:00",
      "summary": "Drone activity (alert) at Орловская область",
      "timestamp": "2026-07-07T16:40:33+00:00",
      "channel": "lpr1_treugolnik"
    },
    {
      "id": "locatorru/71142:Большое Жирово",
      "location": "Большое Жирово",
      "locationRu": "Большое Жирово",
      "region": "Курская область",
      "lat": 51.963799,
      "lon": 35.964409,
      "geocodeSource": "nominatim",
      "geocodePrecision": "point",
      "matchedName": "Большое Жирово",
      "threatType": "drone",
      "count": null,
      "heading": null,
      "destination": "Троснянского",
      "destinationLat": 52.4481203,
      "destinationLon": 35.7788917,
      "bearing": 346.86281455150254,
      "status": "approaching",
      "confidence": 0.55,
      "postId": 71142,
      "postLink": "https://t.me/locatorru/71142",
      "postText": "Большое Жирово, Фатежский район, Курская область - пролёты БПЛА в сторону Троснянского района, Глазуновского района, Колпнянского района, Орловской области. Много.\n\n📡Локатор России - @locatorru",
      "postDate": "2026-07-07T16:43:45+00:00",
      "summary": "Drone activity (approaching) at Большое Жирово, Фатежский район",
      "timestamp": "2026-07-07T16:43:45+00:00",
      "channel": "locatorru"
    },
    {
      "id": "locatorru/71142:Фатежский район",
      "location": "Фатежский район",
      "locationRu": "Фатежский район",
      "region": "Курская область",
      "lat": 52.2925518,
      "lon": 35.820969,
      "geocodeSource": "nominatim",
      "geocodePrecision": "point",
      "matchedName": "Курская область",
      "threatType": "drone",
      "count": null,
      "heading": null,
      "destination": "Троснянского",
      "destinationLat": 52.4481203,
      "destinationLon": 35.7788917,
      "bearing": 350.6394882291038,
      "status": "approaching",
      "confidence": 0.55,
      "postId": 71142,
      "postLink": "https://t.me/locatorru/71142",
      "postText": "Большое Жирово, Фатежский район, Курская область - пролёты БПЛА в сторону Троснянского района, Глазуновского района, Колпнянского района, Орловской области. Много.\n\n📡Локатор России - @locatorru",
      "postDate": "2026-07-07T16:43:45+00:00",
      "summary": "Drone activity (approaching) at Большое Жирово, Фатежский район",
      "timestamp": "2026-07-07T16:43:45+00:00",
      "channel": "locatorru"
    },
    {
      "id": "lpr1_treugolnik/240126:Рубежное",
      "location": "Рубежное",
      "locationRu": "Рубежное",
      "region": "",
      "lat": 49.0329045,
      "lon": 38.3725819,
      "geocodeSource": "nominatim",
      "geocodePrecision": "point",
      "matchedName": "Rubizhne",
      "threatType": "drone",
      "count": null,
      "heading": null,
      "destination": null,
      "destinationLat": null,
      "destinationLon": null,
      "bearing": null,
      "status": "alert",
      "confidence": 0.55,
      "postId": 240126,
      "postLink": "https://t.me/lpr1_treugolnik/240126",
      "postText": "Рубежное\nЛНР\nОпасность по БПЛА",
      "postDate": "2026-07-07T16:52:55+00:00",
      "summary": "Drone activity (alert) at Рубежное, ЛНР",
      "timestamp": "2026-07-07T16:52:55+00:00",
      "channel": "lpr1_treugolnik"
    },
    {
      "id": "lpr1_treugolnik/240126:ЛНР",
      "location": "ЛНР",
      "locationRu": "ЛНР",
      "region": "",
      "lat": 48.5235152,
      "lon": 39.2864367,
      "geocodeSource": "nominatim",
      "geocodePrecision": "point",
      "matchedName": "СП ФАРМФАБРИКА ГУП \"ЛУГМЕДФАРМ\"",
      "threatType": "drone",
      "count": null,
      "heading": null,
      "destination": null,
      "destinationLat": null,
      "destinationLon": null,
      "bearing": null,
      "status": "alert",
      "confidence": 0.55,
      "postId": 240126,
      "postLink": "https://t.me/lpr1_treugolnik/240126",
      "postText": "Рубежное\nЛНР\nОпасность по БПЛА",
      "postDate": "2026-07-07T16:52:55+00:00",
      "summary": "Drone activity (alert) at Рубежное, ЛНР",
      "timestamp": "2026-07-07T16:52:55+00:00",
      "channel": "lpr1_treugolnik"
    },
    {
      "id": "radarrussiia/80530:Новороссийск и близлежащие",
      "location": "Новороссийск и близлежащие",
      "locationRu": "Новороссийск и близлежащие",
      "region": "Краснодарский край",
      "lat": 45.5,
      "lon": 39.5,
      "geocodeSource": "gazetteer-region",
      "geocodePrecision": "region",
      "matchedName": "Krasnodar Krai",
      "threatType": "drone",
      "count": null,
      "heading": null,
      "destination": null,
      "destinationLat": null,
      "destinationLon": null,
      "bearing": null,
      "status": "all_clear",
      "confidence": 0.55,
      "postId": 80530,
      "postLink": "https://t.me/radarrussiia/80530",
      "postText": "Новороссийск и близлежащие\nКраснодарский край\nОтбой опасности по БПЛА\nНа территории региона опасность сохраняется\n\n❗️Радар по всей России - @radarrussiia\n🌐 Обход белых списков - @Internet_Boost_bot",
      "postDate": "2026-07-07T16:57:20+00:00",
      "summary": "Drone activity (all_clear) at Новороссийск и близлежащие",
      "timestamp": "2026-07-07T16:57:20+00:00",
      "channel": "radarrussiia"
    },
    {
      "id": "locatorru/71144:Ростовская область",
      "location": "Ростовская область",
      "locationRu": "Ростовская область",
      "region": "Ростовская область",
      "lat": 47.7,
      "lon": 41,
      "geocodeSource": "gazetteer",
      "geocodePrecision": "point",
      "matchedName": "Rostov Oblast",
      "threatType": "drone",
      "count": null,
      "heading": null,
      "destination": null,
      "destinationLat": null,
      "destinationLon": null,
      "bearing": null,
      "status": "alert",
      "confidence": 0.55,
      "postId": 71144,
      "postLink": "https://t.me/locatorru/71144",
      "postText": "Ростовская область - опасность по БПЛА.\n\n📡Локатор России - @locatorru",
      "postDate": "2026-07-07T17:07:09+00:00",
      "summary": "Drone activity (alert) at Ростовская область",
      "timestamp": "2026-07-07T17:07:09+00:00",
      "channel": "locatorru"
    },
    {
      "id": "radarrussiia/80531:Ростовская область",
      "location": "Ростовская область",
      "locationRu": "Ростовская область",
      "region": "Ростовская область",
      "lat": 47.7,
      "lon": 41,
      "geocodeSource": "gazetteer",
      "geocodePrecision": "point",
      "matchedName": "Rostov Oblast",
      "threatType": "drone",
      "count": null,
      "heading": null,
      "destination": null,
      "destinationLat": null,
      "destinationLon": null,
      "bearing": null,
      "status": "alert",
      "confidence": 0.55,
      "postId": 80531,
      "postLink": "https://t.me/radarrussiia/80531",
      "postText": "Ростовская область\nОпасность по БПЛА\n\n❗️Радар по всей России - @radarrussiia\n🌐 Обход белых списков - @Internet_Boost_bot",
      "postDate": "2026-07-07T17:11:42+00:00",
      "summary": "Drone activity (alert) at Ростовская область",
      "timestamp": "2026-07-07T17:11:42+00:00",
      "channel": "radarrussiia"
    },
    {
      "id": "radarrussiia/80532:Орловская область",
      "location": "Орловская область",
      "locationRu": "Орловская область",
      "region": "Орловская область",
      "lat": 52.4316213,
      "lon": 35.6043309,
      "geocodeSource": "nominatim",
      "geocodePrecision": "point",
      "matchedName": "Орловская область",
      "threatType": "drone",
      "count": null,
      "heading": null,
      "destination": null,
      "destinationLat": null,
      "destinationLon": null,
      "bearing": null,
      "status": "alert",
      "confidence": 0.55,
      "postId": 80532,
      "postLink": "https://t.me/radarrussiia/80532",
      "postText": "Орловская область\nТревога по БПЛА от Курской области\n\n❗️Радар по всей России - @radarrussiia\n🌐 Обход белых списков - @Internet_Boost_bot",
      "postDate": "2026-07-07T17:12:41+00:00",
      "summary": "Drone activity (alert) at Орловская область",
      "timestamp": "2026-07-07T17:12:41+00:00",
      "channel": "radarrussiia"
    },
    {
      "id": "lpr1_treugolnik/240129:Новотроицкий район",
      "location": "Новотроицкий район",
      "locationRu": "Новотроицкий район",
      "region": "",
      "lat": 46.3982174,
      "lon": 34.3266739,
      "geocodeSource": "nominatim",
      "geocodePrecision": "point",
      "matchedName": "Novotroitske Raion",
      "threatType": "drone",
      "count": null,
      "heading": null,
      "destination": "Великая Лепетиха",
      "destinationLat": 47.178599,
      "destinationLon": 33.9428266,
      "bearing": 341.5271059731599,
      "status": "alert",
      "confidence": 0.55,
      "postId": 240129,
      "postLink": "https://t.me/lpr1_treugolnik/240129",
      "postText": "Князе-Григоровка Херсонская область РФ и далее на юг, юго-восток тревога по БПЛА в направлении Великая Лепетиха, Новотроицкий район, Генический и в направлении Мелитополь",
      "postDate": "2026-07-07T17:16:31+00:00",
      "summary": "Drone activity (alert) at Новотроицкий район",
      "timestamp": "2026-07-07T17:16:31+00:00",
      "channel": "lpr1_treugolnik"
    },
    {
      "id": "radarrussiia/80534:Чертковский район",
      "location": "Чертковский район",
      "locationRu": "Чертковский район",
      "region": "Ростовская область",
      "lat": 49.5896375,
      "lon": 40.5547117,
      "geocodeSource": "nominatim",
      "geocodePrecision": "point",
      "matchedName": "Чертковский район",
      "threatType": "drone",
      "count": 2,
      "heading": null,
      "destination": null,
      "destinationLat": null,
      "destinationLon": null,
      "bearing": null,
      "status": "approaching",
      "confidence": 0.55,
      "postId": 80534,
      "postLink": "https://t.me/radarrussiia/80534",
      "postText": "Чертковский район\nРостовская область\nФиксация от 2 БПЛА\n\n❗️Радар по всей России - @radarrussiia\n🌐 Обход белых списков - @Internet_Boost_bot",
      "postDate": "2026-07-07T17:18:11+00:00",
      "summary": "Drone activity (approaching) at Чертковский район",
      "timestamp": "2026-07-07T17:18:11+00:00",
      "channel": "radarrussiia"
    },
    {
      "id": "lpr1_treugolnik/240130:Ростовская область",
      "location": "Ростовская область",
      "locationRu": "Ростовская область",
      "region": "Ростовская область",
      "lat": 47.7,
      "lon": 41,
      "geocodeSource": "gazetteer",
      "geocodePrecision": "point",
      "matchedName": "Rostov Oblast",
      "threatType": "drone",
      "count": null,
      "heading": null,
      "destination": null,
      "destinationLat": null,
      "destinationLon": null,
      "bearing": null,
      "status": "alert",
      "confidence": 0.55,
      "postId": 240130,
      "postLink": "https://t.me/lpr1_treugolnik/240130",
      "postText": "Ростовская область\nОпасность по БПЛА",
      "postDate": "2026-07-07T17:20:50+00:00",
      "summary": "Drone activity (alert) at Ростовская область",
      "timestamp": "2026-07-07T17:20:50+00:00",
      "channel": "lpr1_treugolnik"
    },
    {
      "id": "lpr1_treugolnik/240131:Курская область",
      "location": "Курская область",
      "locationRu": "Курская область",
      "region": "Курская область",
      "lat": 51.7,
      "lon": 36.2,
      "geocodeSource": "gazetteer",
      "geocodePrecision": "point",
      "matchedName": "Kursk Oblast",
      "threatType": "drone",
      "count": null,
      "heading": null,
      "destination": null,
      "destinationLat": null,
      "destinationLon": null,
      "bearing": null,
      "status": "alert",
      "confidence": 0.55,
      "postId": 240131,
      "postLink": "https://t.me/lpr1_treugolnik/240131",
      "postText": "Курская область\n\nТревога по БПЛА сохраняется",
      "postDate": "2026-07-07T17:21:59+00:00",
      "summary": "Drone activity (alert) at Курская область",
      "timestamp": "2026-07-07T17:21:59+00:00",
      "channel": "lpr1_treugolnik"
    },
    {
      "id": "lpr1_treugolnik/240132:Орловская область",
      "location": "Орловская область",
      "locationRu": "Орловская область",
      "region": "Орловская область",
      "lat": 52.4316213,
      "lon": 35.6043309,
      "geocodeSource": "nominatim",
      "geocodePrecision": "point",
      "matchedName": "Орловская область",
      "threatType": "drone",
      "count": null,
      "heading": null,
      "destination": null,
      "destinationLat": null,
      "destinationLon": null,
      "bearing": null,
      "status": "approaching",
      "confidence": 0.55,
      "postId": 240132,
      "postLink": "https://t.me/lpr1_treugolnik/240132",
      "postText": "Орловская область\n\nВнимание по БПЛА от Курской области",
      "postDate": "2026-07-07T17:22:42+00:00",
      "summary": "Drone activity (approaching) at Орловская область",
      "timestamp": "2026-07-07T17:22:42+00:00",
      "channel": "lpr1_treugolnik"
    },
    {
      "id": "lpr1_treugolnik/240133:Белгородская область Старый Оскол",
      "location": "Белгородская область Старый Оскол",
      "locationRu": "Белгородская область Старый Оскол",
      "region": "Белгородская область Старый Оскол",
      "lat": 51.3288129,
      "lon": 37.7684547,
      "geocodeSource": "nominatim",
      "geocodePrecision": "point",
      "matchedName": "Stary Oskol Airport",
      "threatType": "drone",
      "count": null,
      "heading": null,
      "destination": null,
      "destinationLat": null,
      "destinationLon": null,
      "bearing": null,
      "status": "alert",
      "confidence": 0.55,
      "postId": 240133,
      "postLink": "https://t.me/lpr1_treugolnik/240133",
      "postText": "Белгородская область Старый Оскол, Губкин от Прохоровки тревога по БПЛА и далее на Воронежскую область",
      "postDate": "2026-07-07T17:23:28+00:00",
      "summary": "Drone activity (alert) at Белгородская область Старый Оскол",
      "timestamp": "2026-07-07T17:23:28+00:00",
      "channel": "lpr1_treugolnik"
    },
    {
      "id": "lpr1_treugolnik/240135:Двулучное",
      "location": "Двулучное",
      "locationRu": "Двулучное",
      "region": "",
      "lat": 50.0370558,
      "lon": 38.0110271,
      "geocodeSource": "nominatim",
      "geocodePrecision": "point",
      "matchedName": "Двулучное",
      "threatType": "drone",
      "count": null,
      "heading": null,
      "destination": null,
      "destinationLat": null,
      "destinationLon": null,
      "bearing": null,
      "status": "alert",
      "confidence": 0.55,
      "postId": 240135,
      "postLink": "https://t.me/lpr1_treugolnik/240135",
      "postText": "Двулучное, Уразово\nВалуйский район\nТревога по БПЛА",
      "postDate": "2026-07-07T17:24:38+00:00",
      "summary": "Drone activity (alert) at Двулучное, Уразово, Валуйский район",
      "timestamp": "2026-07-07T17:24:38+00:00",
      "channel": "lpr1_treugolnik"
    },
    {
      "id": "lpr1_treugolnik/240135:Уразово",
      "location": "Уразово",
      "locationRu": "Уразово",
      "region": "",
      "lat": 54.268032,
      "lon": 59.132694,
      "geocodeSource": "nominatim",
      "geocodePrecision": "point",
      "matchedName": "Urazovo",
      "threatType": "drone",
      "count": null,
      "heading": null,
      "destination": null,
      "destinationLat": null,
      "destinationLon": null,
      "bearing": null,
      "status": "alert",
      "confidence": 0.55,
      "postId": 240135,
      "postLink": "https://t.me/lpr1_treugolnik/240135",
      "postText": "Двулучное, Уразово\nВалуйский район\nТревога по БПЛА",
      "postDate": "2026-07-07T17:24:38+00:00",
      "summary": "Drone activity (alert) at Двулучное, Уразово, Валуйский район",
      "timestamp": "2026-07-07T17:24:38+00:00",
      "channel": "lpr1_treugolnik"
    },
    {
      "id": "lpr1_treugolnik/240135:Валуйский район",
      "location": "Валуйский район",
      "locationRu": "Валуйский район",
      "region": "",
      "lat": 53.1481885,
      "lon": 36.3185713,
      "geocodeSource": "nominatim",
      "geocodePrecision": "point",
      "matchedName": "Валуйский",
      "threatType": "drone",
      "count": null,
      "heading": null,
      "destination": null,
      "destinationLat": null,
      "destinationLon": null,
      "bearing": null,
      "status": "alert",
      "confidence": 0.55,
      "postId": 240135,
      "postLink": "https://t.me/lpr1_treugolnik/240135",
      "postText": "Двулучное, Уразово\nВалуйский район\nТревога по БПЛА",
      "postDate": "2026-07-07T17:24:38+00:00",
      "summary": "Drone activity (alert) at Двулучное, Уразово, Валуйский район",
      "timestamp": "2026-07-07T17:24:38+00:00",
      "channel": "lpr1_treugolnik"
    },
    {
      "id": "lpr1_treugolnik/240136:Ботиево",
      "location": "Ботиево",
      "locationRu": "Ботиево",
      "region": "",
      "lat": 46.682968,
      "lon": 35.842548,
      "geocodeSource": "nominatim",
      "geocodePrecision": "point",
      "matchedName": "Botiieve",
      "threatType": "drone",
      "count": null,
      "heading": null,
      "destination": null,
      "destinationLat": null,
      "destinationLon": null,
      "bearing": null,
      "status": "alert",
      "confidence": 0.55,
      "postId": 240136,
      "postLink": "https://t.me/lpr1_treugolnik/240136",
      "postText": "Ботиево, Приморский Посад Запорожская область РФ тревога по БПЛА на электротяге и далее в Азовское море",
      "postDate": "2026-07-07T17:25:08+00:00",
      "summary": "Drone activity (alert) at Ботиево",
      "timestamp": "2026-07-07T17:25:08+00:00",
      "channel": "lpr1_treugolnik"
    },
    {
      "id": "locatorru/71146:Белгородская область",
      "location": "Белгородская область",
      "locationRu": "Белгородская область",
      "region": "Белгородская область",
      "lat": 50.7,
      "lon": 37.6,
      "geocodeSource": "gazetteer",
      "geocodePrecision": "point",
      "matchedName": "Belgorod Oblast",
      "threatType": "drone",
      "count": null,
      "heading": null,
      "destination": null,
      "destinationLat": null,
      "destinationLon": null,
      "bearing": null,
      "status": "alert",
      "confidence": 0.55,
      "postId": 71146,
      "postLink": "https://t.me/locatorru/71146",
      "postText": "Белгородская область - опасность по БПЛА.\nОт Харьковской области и Курской области.\n\n📡Локатор России - @locatorru",
      "postDate": "2026-07-07T17:25:11+00:00",
      "summary": "Drone activity (alert) at Белгородская область",
      "timestamp": "2026-07-07T17:25:11+00:00",
      "channel": "locatorru"
    },
    {
      "id": "locatorru/71147:Валуйский район",
      "location": "Валуйский район",
      "locationRu": "Валуйский район",
      "region": "Белгородская область",
      "lat": 50.7,
      "lon": 37.6,
      "geocodeSource": "gazetteer-region",
      "geocodePrecision": "region",
      "matchedName": "Belgorod Oblast",
      "threatType": "drone",
      "count": null,
      "heading": null,
      "destination": null,
      "destinationLat": null,
      "destinationLon": null,
      "bearing": null,
      "status": "approaching",
      "confidence": 0.55,
      "postId": 71147,
      "postLink": "https://t.me/locatorru/71147",
      "postText": "Валуйский район, Белгородская область - фиксации БПЛА от Харькова.\n\n📡Локатор России - @locatorru",
      "postDate": "2026-07-07T17:25:31+00:00",
      "summary": "Drone activity (approaching) at Валуйский район",
      "timestamp": "2026-07-07T17:25:31+00:00",
      "channel": "locatorru"
    },
    {
      "id": "lpr1_treugolnik/240137:Красная яруга",
      "location": "Красная яруга",
      "locationRu": "Красная яруга",
      "region": "",
      "lat": 50.800701,
      "lon": 35.655228,
      "geocodeSource": "nominatim",
      "geocodePrecision": "point",
      "matchedName": "Krasnaya Yaruga",
      "threatType": "drone",
      "count": null,
      "heading": null,
      "destination": null,
      "destinationLat": null,
      "destinationLon": null,
      "bearing": null,
      "status": "alert",
      "confidence": 0.55,
      "postId": 240137,
      "postLink": "https://t.me/lpr1_treugolnik/240137",
      "postText": "Красная яруга\nТревога по БПЛА",
      "postDate": "2026-07-07T17:25:35+00:00",
      "summary": "Drone activity (alert) at Красная яруга",
      "timestamp": "2026-07-07T17:25:35+00:00",
      "channel": "lpr1_treugolnik"
    },
    {
      "id": "locatorru/71148:Пристень",
      "location": "Пристень",
      "locationRu": "Пристень",
      "region": "Курская область",
      "lat": 51.236023,
      "lon": 36.6941094,
      "geocodeSource": "nominatim",
      "geocodePrecision": "point",
      "matchedName": "Pristen",
      "threatType": "drone",
      "count": null,
      "heading": null,
      "destination": "Архангельское",
      "destinationLat": 54.068245,
      "destinationLon": 56.408726,
      "bearing": 68.93854170873686,
      "status": "approaching",
      "confidence": 0.55,
      "postId": 71148,
      "postLink": "https://t.me/locatorru/71148",
      "postText": "Пристень, Солнцево, Курская область - фиксации БПЛА в сторону Архангельское, Губкин, Старый Оскол, Федосеевка, Обуховка, Белгородская область.\n\n📡Локатор России - @locatorru",
      "postDate": "2026-07-07T17:26:57+00:00",
      "summary": "Drone activity (approaching) at Пристень, Солнцево",
      "timestamp": "2026-07-07T17:26:57+00:00",
      "channel": "locatorru"
    },
    {
      "id": "locatorru/71148:Солнцево",
      "location": "Солнцево",
      "locationRu": "Солнцево",
      "region": "Курская область",
      "lat": 51.419552,
      "lon": 36.749901,
      "geocodeSource": "nominatim",
      "geocodePrecision": "point",
      "matchedName": "Solintsevo",
      "threatType": "drone",
      "count": null,
      "heading": null,
      "destination": "Архангельское",
      "destinationLat": 54.068245,
      "destinationLon": 56.408726,
      "bearing": 69.71950073224224,
      "status": "approaching",
      "confidence": 0.55,
      "postId": 71148,
      "postLink": "https://t.me/locatorru/71148",
      "postText": "Пристень, Солнцево, Курская область - фиксации БПЛА в сторону Архангельское, Губкин, Старый Оскол, Федосеевка, Обуховка, Белгородская область.\n\n📡Локатор России - @locatorru",
      "postDate": "2026-07-07T17:26:57+00:00",
      "summary": "Drone activity (approaching) at Пристень, Солнцево",
      "timestamp": "2026-07-07T17:26:57+00:00",
      "channel": "locatorru"
    },
    {
      "id": "locatorru/71149:Череповец",
      "location": "Череповец",
      "locationRu": "Череповец",
      "region": "Вологодская область",
      "lat": 59.1221553,
      "lon": 37.9025005,
      "geocodeSource": "nominatim",
      "geocodePrecision": "point",
      "matchedName": "Cherepovets",
      "threatType": "drone",
      "count": null,
      "heading": null,
      "destination": null,
      "destinationLat": null,
      "destinationLon": null,
      "bearing": null,
      "status": "alert",
      "confidence": 0.55,
      "postId": 71149,
      "postLink": "https://t.me/locatorru/71149",
      "postText": "Череповец, Вологодская область - опасность по БПЛА.\n\n📡Локатор России - @locatorru",
      "postDate": "2026-07-07T17:30:25+00:00",
      "summary": "Drone activity (alert) at Череповец",
      "timestamp": "2026-07-07T17:30:25+00:00",
      "channel": "locatorru"
    },
    {
      "id": "radarrussiia/80535:Череповец",
      "location": "Череповец",
      "locationRu": "Череповец",
      "region": "Вологодская область",
      "lat": 59.1221553,
      "lon": 37.9025005,
      "geocodeSource": "nominatim",
      "geocodePrecision": "point",
      "matchedName": "Cherepovets",
      "threatType": "drone",
      "count": null,
      "heading": null,
      "destination": null,
      "destinationLat": null,
      "destinationLon": null,
      "bearing": null,
      "status": "alert",
      "confidence": 0.55,
      "postId": 80535,
      "postLink": "https://t.me/radarrussiia/80535",
      "postText": "Череповец, Вологодская область - опасность по БПЛА\n\n❗️Радар по всей России - @radarrussiia\n🌐 Обход белых списков - @Internet_Boost_bot",
      "postDate": "2026-07-07T17:31:19+00:00",
      "summary": "Drone activity (alert) at Череповец",
      "timestamp": "2026-07-07T17:31:19+00:00",
      "channel": "radarrussiia"
    }
  ],
  "lastPostId": {
    "radarrussiia": 80535,
    "kpszsu": 67665,
    "lpr1_treugolnik": 240140,
    "locatorru": 71149
  },
  "updatedAt": "2026-07-07T17:32:19.165Z"
}