{
  "sightings": [
    {
      "id": "lpr1_treugolnik/245567:Клинцы",
      "location": "Клинцы",
      "locationRu": "Клинцы",
      "region": "Брянская область",
      "lat": 52.7494,
      "lon": 32.2356,
      "geocodeSource": "gazetteer",
      "geocodePrecision": "point",
      "matchedName": "Klintsy",
      "threatType": "drone",
      "count": null,
      "heading": null,
      "destination": null,
      "destinationLat": null,
      "destinationLon": null,
      "bearing": null,
      "status": "alert",
      "confidence": 0.55,
      "postId": 245567,
      "postLink": "https://t.me/lpr1_treugolnik/245567",
      "postText": "Клинцы, Брянская область\nОпасность по БПЛА",
      "postDate": "2026-07-18T16:42:52+00:00",
      "summary": "Drone activity (alert) at Клинцы",
      "timestamp": "2026-07-18T16:42:52+00:00",
      "channel": "lpr1_treugolnik"
    },
    {
      "id": "locatorru/73170:Новозыбков",
      "location": "Новозыбков",
      "locationRu": "Новозыбков",
      "region": "",
      "lat": 52.5353,
      "lon": 31.9342,
      "geocodeSource": "gazetteer",
      "geocodePrecision": "point",
      "matchedName": "Novozybkov",
      "threatType": "drone",
      "count": null,
      "heading": null,
      "destination": null,
      "destinationLat": null,
      "destinationLon": null,
      "bearing": null,
      "status": "unknown",
      "confidence": 0.55,
      "postId": 73170,
      "postLink": "https://t.me/locatorru/73170",
      "postText": "Новозыбков, Климово, Клинцы, внимание по единичным БПЛА сохраняется.\n\n📡Локатор России - @locatorru",
      "postDate": "2026-07-18T16:43:50+00:00",
      "summary": "Drone activity (unknown) at Новозыбков, Климово, Клинцы",
      "timestamp": "2026-07-18T16:43:50+00:00",
      "channel": "locatorru"
    },
    {
      "id": "locatorru/73170:Климово",
      "location": "Климово",
      "locationRu": "Климово",
      "region": "",
      "lat": 57.1186361,
      "lon": 35.1441991,
      "geocodeSource": "nominatim",
      "geocodePrecision": "point",
      "matchedName": "Климово",
      "threatType": "drone",
      "count": null,
      "heading": null,
      "destination": null,
      "destinationLat": null,
      "destinationLon": null,
      "bearing": null,
      "status": "unknown",
      "confidence": 0.55,
      "postId": 73170,
      "postLink": "https://t.me/locatorru/73170",
      "postText": "Новозыбков, Климово, Клинцы, внимание по единичным БПЛА сохраняется.\n\n📡Локатор России - @locatorru",
      "postDate": "2026-07-18T16:43:50+00:00",
      "summary": "Drone activity (unknown) at Новозыбков, Климово, Клинцы",
      "timestamp": "2026-07-18T16:43:50+00:00",
      "channel": "locatorru"
    },
    {
      "id": "locatorru/73170:Клинцы",
      "location": "Клинцы",
      "locationRu": "Клинцы",
      "region": "",
      "lat": 52.7494,
      "lon": 32.2356,
      "geocodeSource": "gazetteer",
      "geocodePrecision": "point",
      "matchedName": "Klintsy",
      "threatType": "drone",
      "count": null,
      "heading": null,
      "destination": null,
      "destinationLat": null,
      "destinationLon": null,
      "bearing": null,
      "status": "unknown",
      "confidence": 0.55,
      "postId": 73170,
      "postLink": "https://t.me/locatorru/73170",
      "postText": "Новозыбков, Климово, Клинцы, внимание по единичным БПЛА сохраняется.\n\n📡Локатор России - @locatorru",
      "postDate": "2026-07-18T16:43:50+00:00",
      "summary": "Drone activity (unknown) at Новозыбков, Климово, Клинцы",
      "timestamp": "2026-07-18T16:43:50+00:00",
      "channel": "locatorru"
    },
    {
      "id": "lpr1_treugolnik/245571:Валуйского района",
      "location": "Валуйского района",
      "locationRu": "Валуйского района",
      "region": "",
      "lat": 50.211038,
      "lon": 38.0997012,
      "geocodeSource": "nominatim",
      "geocodePrecision": "point",
      "matchedName": "Администрация города Валуйки и Валуйского района",
      "threatType": "drone",
      "count": null,
      "heading": null,
      "destination": null,
      "destinationLat": null,
      "destinationLon": null,
      "bearing": null,
      "status": "alert",
      "confidence": 0.55,
      "postId": 245571,
      "postLink": "https://t.me/lpr1_treugolnik/245571",
      "postText": "Логачевка Двулучное Уразово\nВалуйского района\nТревога по БПЛА Хорнет",
      "postDate": "2026-07-18T16:52:47+00:00",
      "summary": "Drone activity (alert) at Логачевка Двулучное Уразово, Валуйского района",
      "timestamp": "2026-07-18T16:52:47+00:00",
      "channel": "lpr1_treugolnik"
    },
    {
      "id": "radarrussiia/82591:Рязанский район",
      "location": "Рязанский район",
      "locationRu": "Рязанский район",
      "region": "Рязанская область",
      "lat": 54.7089793,
      "lon": 39.5044541,
      "geocodeSource": "nominatim",
      "geocodePrecision": "point",
      "matchedName": "Рязанский район",
      "threatType": "drone",
      "count": 2,
      "heading": null,
      "destination": null,
      "destinationLat": null,
      "destinationLon": null,
      "bearing": null,
      "status": "approaching",
      "confidence": 0.55,
      "postId": 82591,
      "postLink": "https://t.me/radarrussiia/82591",
      "postText": "Рязанский район\nРязанская область\nФиксация от 2 БПЛА\n\n❗️Радар по всей России - @radarrussiia\n🌐 Обход белых списков - @Internet_Boost_bot",
      "postDate": "2026-07-18T16:52:50+00:00",
      "summary": "Drone activity (approaching) at Рязанский район",
      "timestamp": "2026-07-18T16:52:50+00:00",
      "channel": "radarrussiia"
    },
    {
      "id": "lpr1_treugolnik/245575:Шебекино",
      "location": "Шебекино",
      "locationRu": "Шебекино",
      "region": "",
      "lat": 50.4061,
      "lon": 36.8997,
      "geocodeSource": "gazetteer",
      "geocodePrecision": "point",
      "matchedName": "Shebekino",
      "threatType": "drone",
      "count": null,
      "heading": null,
      "destination": null,
      "destinationLat": null,
      "destinationLon": null,
      "bearing": null,
      "status": "alert",
      "confidence": 0.55,
      "postId": 245575,
      "postLink": "https://t.me/lpr1_treugolnik/245575",
      "postText": "Шебекино\nТревога по БПЛА",
      "postDate": "2026-07-18T17:06:27+00:00",
      "summary": "Drone activity (alert) at Шебекино",
      "timestamp": "2026-07-18T17:06:27+00:00",
      "channel": "lpr1_treugolnik"
    },
    {
      "id": "lpr1_treugolnik/245578:Валуйский район",
      "location": "Валуйский район",
      "locationRu": "Валуйский район",
      "region": "",
      "lat": 53.1481885,
      "lon": 36.3185713,
      "geocodeSource": "nominatim",
      "geocodePrecision": "point",
      "matchedName": "Валуйский",
      "threatType": "drone",
      "count": null,
      "heading": null,
      "destination": null,
      "destinationLat": null,
      "destinationLon": null,
      "bearing": null,
      "status": "alert",
      "confidence": 0.55,
      "postId": 245578,
      "postLink": "https://t.me/lpr1_treugolnik/245578",
      "postText": "Валуйский район\nОпасность атаки БПЛА",
      "postDate": "2026-07-18T17:18:01+00:00",
      "summary": "Drone activity (alert) at Валуйский район",
      "timestamp": "2026-07-18T17:18:01+00:00",
      "channel": "lpr1_treugolnik"
    },
    {
      "id": "locatorru/73171:Тамбовская область",
      "location": "Тамбовская область",
      "locationRu": "Тамбовская область",
      "region": "Тамбовская область",
      "lat": 52.9516117,
      "lon": 42.9107997,
      "geocodeSource": "nominatim",
      "geocodePrecision": "point",
      "matchedName": "Тамбовская область",
      "threatType": "drone",
      "count": null,
      "heading": null,
      "destination": null,
      "destinationLat": null,
      "destinationLon": null,
      "bearing": null,
      "status": "all_clear",
      "confidence": 0.55,
      "postId": 73171,
      "postLink": "https://t.me/locatorru/73171",
      "postText": "Тамбовская область - отбой опасности по БПЛА. Режим внимание.\n\n📡Локатор России - @locatorru",
      "postDate": "2026-07-18T17:19:18+00:00",
      "summary": "Drone activity (all_clear) at Тамбовская область",
      "timestamp": "2026-07-18T17:19:18+00:00",
      "channel": "locatorru"
    },
    {
      "id": "lpr1_treugolnik/245580:Крупец",
      "location": "Крупец",
      "locationRu": "Крупец",
      "region": "Курская область",
      "lat": 51.6226868,
      "lon": 34.3585397,
      "geocodeSource": "nominatim",
      "geocodePrecision": "point",
      "matchedName": "Krupets",
      "threatType": "drone",
      "count": null,
      "heading": null,
      "destination": null,
      "destinationLat": null,
      "destinationLon": null,
      "bearing": null,
      "status": "alert",
      "confidence": 0.55,
      "postId": 245580,
      "postLink": "https://t.me/lpr1_treugolnik/245580",
      "postText": "Рыльск внимание по БПЛА со стороны Крупца !!\nКрупец - тревога по ФПВ\n\nРыльский район\nКурская область",
      "postDate": "2026-07-18T17:21:48+00:00",
      "summary": "Drone activity (alert) at Крупец, Рыльский район",
      "timestamp": "2026-07-18T17:21:48+00:00",
      "channel": "lpr1_treugolnik"
    },
    {
      "id": "lpr1_treugolnik/245580:Рыльский район",
      "location": "Рыльский район",
      "locationRu": "Рыльский район",
      "region": "Курская область",
      "lat": 51.5713767,
      "lon": 34.624021,
      "geocodeSource": "nominatim",
      "geocodePrecision": "point",
      "matchedName": "Rylsky District",
      "threatType": "drone",
      "count": null,
      "heading": null,
      "destination": null,
      "destinationLat": null,
      "destinationLon": null,
      "bearing": null,
      "status": "alert",
      "confidence": 0.55,
      "postId": 245580,
      "postLink": "https://t.me/lpr1_treugolnik/245580",
      "postText": "Рыльск внимание по БПЛА со стороны Крупца !!\nКрупец - тревога по ФПВ\n\nРыльский район\nКурская область",
      "postDate": "2026-07-18T17:21:48+00:00",
      "summary": "Drone activity (alert) at Крупец, Рыльский район",
      "timestamp": "2026-07-18T17:21:48+00:00",
      "channel": "lpr1_treugolnik"
    },
    {
      "id": "lpr1_treugolnik/245581:Николаевка",
      "location": "Николаевка",
      "locationRu": "Николаевка",
      "region": "",
      "lat": 48.8610868,
      "lon": 37.7619191,
      "geocodeSource": "nominatim",
      "geocodePrecision": "point",
      "matchedName": "Mykolaivka",
      "threatType": "drone",
      "count": null,
      "heading": null,
      "destination": null,
      "destinationLat": null,
      "destinationLon": null,
      "bearing": null,
      "status": "alert",
      "confidence": 0.55,
      "postId": 245581,
      "postLink": "https://t.me/lpr1_treugolnik/245581",
      "postText": "Николаевка, Славянский район, тревога по БПЛА Баба Яга\nДНР",
      "postDate": "2026-07-18T17:22:55+00:00",
      "summary": "Drone activity (alert) at Николаевка, Славянский район, ДНР",
      "timestamp": "2026-07-18T17:22:55+00:00",
      "channel": "lpr1_treugolnik"
    },
    {
      "id": "lpr1_treugolnik/245581:Славянский район",
      "location": "Славянский район",
      "locationRu": "Славянский район",
      "region": "",
      "lat": 45.432373,
      "lon": 37.8218601,
      "geocodeSource": "nominatim",
      "geocodePrecision": "point",
      "matchedName": "Slavyansky District",
      "threatType": "drone",
      "count": null,
      "heading": null,
      "destination": null,
      "destinationLat": null,
      "destinationLon": null,
      "bearing": null,
      "status": "alert",
      "confidence": 0.55,
      "postId": 245581,
      "postLink": "https://t.me/lpr1_treugolnik/245581",
      "postText": "Николаевка, Славянский район, тревога по БПЛА Баба Яга\nДНР",
      "postDate": "2026-07-18T17:22:55+00:00",
      "summary": "Drone activity (alert) at Николаевка, Славянский район, ДНР",
      "timestamp": "2026-07-18T17:22:55+00:00",
      "channel": "lpr1_treugolnik"
    },
    {
      "id": "lpr1_treugolnik/245581:ДНР",
      "location": "ДНР",
      "locationRu": "ДНР",
      "region": "",
      "lat": 48.0162306,
      "lon": 37.8094819,
      "geocodeSource": "nominatim",
      "geocodePrecision": "point",
      "matchedName": "Сектор Міграційної служби Ворошилівського районного відділу Донецького МУ МВД",
      "threatType": "drone",
      "count": null,
      "heading": null,
      "destination": null,
      "destinationLat": null,
      "destinationLon": null,
      "bearing": null,
      "status": "alert",
      "confidence": 0.55,
      "postId": 245581,
      "postLink": "https://t.me/lpr1_treugolnik/245581",
      "postText": "Николаевка, Славянский район, тревога по БПЛА Баба Яга\nДНР",
      "postDate": "2026-07-18T17:22:55+00:00",
      "summary": "Drone activity (alert) at Николаевка, Славянский район, ДНР",
      "timestamp": "2026-07-18T17:22:55+00:00",
      "channel": "lpr1_treugolnik"
    },
    {
      "id": "lpr1_treugolnik/245582:Севастополь",
      "location": "Севастополь",
      "locationRu": "Севастополь",
      "region": "",
      "lat": 44.6166,
      "lon": 33.5254,
      "geocodeSource": "gazetteer",
      "geocodePrecision": "point",
      "matchedName": "Sevastopol",
      "threatType": "drone",
      "count": null,
      "heading": null,
      "destination": null,
      "destinationLat": null,
      "destinationLon": null,
      "bearing": null,
      "status": "alert",
      "confidence": 0.55,
      "postId": 245582,
      "postLink": "https://t.me/lpr1_treugolnik/245582",
      "postText": "Кача и близлежащие\nСевастополь\nТревога по БПЛА с моря",
      "postDate": "2026-07-18T17:22:59+00:00",
      "summary": "Drone activity (alert) at Кача и близлежащие, Севастополь",
      "timestamp": "2026-07-18T17:22:59+00:00",
      "channel": "lpr1_treugolnik"
    },
    {
      "id": "lpr1_treugolnik/245583:Кача",
      "location": "Кача",
      "locationRu": "Кача",
      "region": "",
      "lat": 44.7556354,
      "lon": 33.7235003,
      "geocodeSource": "nominatim",
      "geocodePrecision": "point",
      "matchedName": "Кача",
      "threatType": "drone",
      "count": null,
      "heading": null,
      "destination": null,
      "destinationLat": null,
      "destinationLon": null,
      "bearing": null,
      "status": "alert",
      "confidence": 0.55,
      "postId": 245583,
      "postLink": "https://t.me/lpr1_treugolnik/245583",
      "postText": "Кача, Бельбек, Северная сторона Севастополя\nТревога по БПЛА с моря",
      "postDate": "2026-07-18T17:27:19+00:00",
      "summary": "Drone activity (alert) at Кача, Бельбек, Северная сторона Севастополя",
      "timestamp": "2026-07-18T17:27:19+00:00",
      "channel": "lpr1_treugolnik"
    },
    {
      "id": "lpr1_treugolnik/245583:Бельбек",
      "location": "Бельбек",
      "locationRu": "Бельбек",
      "region": "",
      "lat": 44.6866456,
      "lon": 33.5669965,
      "geocodeSource": "nominatim",
      "geocodePrecision": "point",
      "matchedName": "Sevastopol International Airport",
      "threatType": "drone",
      "count": null,
      "heading": null,
      "destination": null,
      "destinationLat": null,
      "destinationLon": null,
      "bearing": null,
      "status": "alert",
      "confidence": 0.55,
      "postId": 245583,
      "postLink": "https://t.me/lpr1_treugolnik/245583",
      "postText": "Кача, Бельбек, Северная сторона Севастополя\nТревога по БПЛА с моря",
      "postDate": "2026-07-18T17:27:19+00:00",
      "summary": "Drone activity (alert) at Кача, Бельбек, Северная сторона Севастополя",
      "timestamp": "2026-07-18T17:27:19+00:00",
      "channel": "lpr1_treugolnik"
    },
    {
      "id": "lpr1_treugolnik/245583:Северная сторона Севастополя",
      "location": "Северная сторона Севастополя",
      "locationRu": "Северная сторона Севастополя",
      "region": "",
      "lat": 44.6300319,
      "lon": 33.5409422,
      "geocodeSource": "nominatim",
      "geocodePrecision": "point",
      "matchedName": "РОВД Нахимовского района г. Севастополя",
      "threatType": "drone",
      "count": null,
      "heading": null,
      "destination": null,
      "destinationLat": null,
      "destinationLon": null,
      "bearing": null,
      "status": "alert",
      "confidence": 0.55,
      "postId": 245583,
      "postLink": "https://t.me/lpr1_treugolnik/245583",
      "postText": "Кача, Бельбек, Северная сторона Севастополя\nТревога по БПЛА с моря",
      "postDate": "2026-07-18T17:27:19+00:00",
      "summary": "Drone activity (alert) at Кача, Бельбек, Северная сторона Севастополя",
      "timestamp": "2026-07-18T17:27:19+00:00",
      "channel": "lpr1_treugolnik"
    },
    {
      "id": "locatorru/73172:Московская область",
      "location": "Московская область",
      "locationRu": "Московская область",
      "region": "Московская область",
      "lat": 55.2676587,
      "lon": 36.6925436,
      "geocodeSource": "nominatim",
      "geocodePrecision": "point",
      "matchedName": "«Московская область»",
      "threatType": "drone",
      "count": null,
      "heading": null,
      "destination": null,
      "destinationLat": null,
      "destinationLon": null,
      "bearing": null,
      "status": "alert",
      "confidence": 0.55,
      "postId": 73172,
      "postLink": "https://t.me/locatorru/73172",
      "postText": "Московская область - опасность по БПЛА.\n\n📡Локатор России - @locatorru",
      "postDate": "2026-07-18T17:32:02+00:00",
      "summary": "Drone activity (alert) at Московская область",
      "timestamp": "2026-07-18T17:32:02+00:00",
      "channel": "locatorru"
    },
    {
      "id": "locatorru/73173:Таганрог",
      "location": "Таганрог",
      "locationRu": "Таганрог",
      "region": "Краснодарский край",
      "lat": 47.2362,
      "lon": 38.8969,
      "geocodeSource": "gazetteer",
      "geocodePrecision": "point",
      "matchedName": "Taganrog",
      "threatType": "drone",
      "count": null,
      "heading": null,
      "destination": null,
      "destinationLat": null,
      "destinationLon": null,
      "bearing": null,
      "status": "alert",
      "confidence": 0.55,
      "postId": 73173,
      "postLink": "https://t.me/locatorru/73173",
      "postText": "В акваторию Азовского моря выходы БПЛА от Запорожской области РФ.\n\nТаганрогский залив, Таганрог, Азов, Ростовская область / Ейск, Приморско-Ахтарск, Славянск-на-Кубани, Краснодарский край - опасность по БПЛА от Азовского моря.\n\n📡Локатор России - @locatorru",
      "postDate": "2026-07-18T17:34:48+00:00",
      "summary": "Drone activity (alert) at Таганрог, Азов, Приморско-Ахтарск, Славянск-на-Кубани",
      "timestamp": "2026-07-18T17:34:48+00:00",
      "channel": "locatorru"
    },
    {
      "id": "locatorru/73173:Азов",
      "location": "Азов",
      "locationRu": "Азов",
      "region": "Краснодарский край",
      "lat": 47.1056,
      "lon": 39.4231,
      "geocodeSource": "gazetteer",
      "geocodePrecision": "point",
      "matchedName": "Azov",
      "threatType": "drone",
      "count": null,
      "heading": null,
      "destination": null,
      "destinationLat": null,
      "destinationLon": null,
      "bearing": null,
      "status": "alert",
      "confidence": 0.55,
      "postId": 73173,
      "postLink": "https://t.me/locatorru/73173",
      "postText": "В акваторию Азовского моря выходы БПЛА от Запорожской области РФ.\n\nТаганрогский залив, Таганрог, Азов, Ростовская область / Ейск, Приморско-Ахтарск, Славянск-на-Кубани, Краснодарский край - опасность по БПЛА от Азовского моря.\n\n📡Локатор России - @locatorru",
      "postDate": "2026-07-18T17:34:48+00:00",
      "summary": "Drone activity (alert) at Таганрог, Азов, Приморско-Ахтарск, Славянск-на-Кубани",
      "timestamp": "2026-07-18T17:34:48+00:00",
      "channel": "locatorru"
    },
    {
      "id": "locatorru/73173:Приморско-Ахтарск",
      "location": "Приморско-Ахтарск",
      "locationRu": "Приморско-Ахтарск",
      "region": "Краснодарский край",
      "lat": 46.0461,
      "lon": 38.1719,
      "geocodeSource": "gazetteer",
      "geocodePrecision": "point",
      "matchedName": "Primorsko-Akhtarsk",
      "threatType": "drone",
      "count": null,
      "heading": null,
      "destination": null,
      "destinationLat": null,
      "destinationLon": null,
      "bearing": null,
      "status": "alert",
      "confidence": 0.55,
      "postId": 73173,
      "postLink": "https://t.me/locatorru/73173",
      "postText": "В акваторию Азовского моря выходы БПЛА от Запорожской области РФ.\n\nТаганрогский залив, Таганрог, Азов, Ростовская область / Ейск, Приморско-Ахтарск, Славянск-на-Кубани, Краснодарский край - опасность по БПЛА от Азовского моря.\n\n📡Локатор России - @locatorru",
      "postDate": "2026-07-18T17:34:48+00:00",
      "summary": "Drone activity (alert) at Таганрог, Азов, Приморско-Ахтарск, Славянск-на-Кубани",
      "timestamp": "2026-07-18T17:34:48+00:00",
      "channel": "locatorru"
    },
    {
      "id": "locatorru/73173:Славянск-на-Кубани",
      "location": "Славянск-на-Кубани",
      "locationRu": "Славянск-на-Кубани",
      "region": "Краснодарский край",
      "lat": 45.2614,
      "lon": 38.1281,
      "geocodeSource": "gazetteer",
      "geocodePrecision": "point",
      "matchedName": "Slavyansk-na-Kubani",
      "threatType": "drone",
      "count": null,
      "heading": null,
      "destination": null,
      "destinationLat": null,
      "destinationLon": null,
      "bearing": null,
      "status": "alert",
      "confidence": 0.55,
      "postId": 73173,
      "postLink": "https://t.me/locatorru/73173",
      "postText": "В акваторию Азовского моря выходы БПЛА от Запорожской области РФ.\n\nТаганрогский залив, Таганрог, Азов, Ростовская область / Ейск, Приморско-Ахтарск, Славянск-на-Кубани, Краснодарский край - опасность по БПЛА от Азовского моря.\n\n📡Локатор России - @locatorru",
      "postDate": "2026-07-18T17:34:48+00:00",
      "summary": "Drone activity (alert) at Таганрог, Азов, Приморско-Ахтарск, Славянск-на-Кубани",
      "timestamp": "2026-07-18T17:34:48+00:00",
      "channel": "locatorru"
    },
    {
      "id": "lpr1_treugolnik/245591:Фиолент",
      "location": "Фиолент",
      "locationRu": "Фиолент",
      "region": "",
      "lat": 44.9613356,
      "lon": 34.1043495,
      "geocodeSource": "nominatim",
      "geocodePrecision": "point",
      "matchedName": "Фиолент",
      "threatType": "drone",
      "count": null,
      "heading": null,
      "destination": null,
      "destinationLat": null,
      "destinationLon": null,
      "bearing": null,
      "status": "approaching",
      "confidence": 0.55,
      "postId": 245591,
      "postLink": "https://t.me/lpr1_treugolnik/245591",
      "postText": "Фиолент, Балаклава\nСевастополь\nС моря возможно фиксации БПЛА",
      "postDate": "2026-07-18T17:37:55+00:00",
      "summary": "Drone activity (approaching) at Фиолент, Балаклава, Севастополь",
      "timestamp": "2026-07-18T17:37:55+00:00",
      "channel": "lpr1_treugolnik"
    },
    {
      "id": "lpr1_treugolnik/245591:Балаклава",
      "location": "Балаклава",
      "locationRu": "Балаклава",
      "region": "",
      "lat": 44.5121316,
      "lon": 33.5990374,
      "geocodeSource": "nominatim",
      "geocodePrecision": "point",
      "matchedName": "Balaklava",
      "threatType": "drone",
      "count": null,
      "heading": null,
      "destination": null,
      "destinationLat": null,
      "destinationLon": null,
      "bearing": null,
      "status": "approaching",
      "confidence": 0.55,
      "postId": 245591,
      "postLink": "https://t.me/lpr1_treugolnik/245591",
      "postText": "Фиолент, Балаклава\nСевастополь\nС моря возможно фиксации БПЛА",
      "postDate": "2026-07-18T17:37:55+00:00",
      "summary": "Drone activity (approaching) at Фиолент, Балаклава, Севастополь",
      "timestamp": "2026-07-18T17:37:55+00:00",
      "channel": "lpr1_treugolnik"
    },
    {
      "id": "lpr1_treugolnik/245591:Севастополь",
      "location": "Севастополь",
      "locationRu": "Севастополь",
      "region": "",
      "lat": 44.6166,
      "lon": 33.5254,
      "geocodeSource": "gazetteer",
      "geocodePrecision": "point",
      "matchedName": "Sevastopol",
      "threatType": "drone",
      "count": null,
      "heading": null,
      "destination": null,
      "destinationLat": null,
      "destinationLon": null,
      "bearing": null,
      "status": "approaching",
      "confidence": 0.55,
      "postId": 245591,
      "postLink": "https://t.me/lpr1_treugolnik/245591",
      "postText": "Фиолент, Балаклава\nСевастополь\nС моря возможно фиксации БПЛА",
      "postDate": "2026-07-18T17:37:55+00:00",
      "summary": "Drone activity (approaching) at Фиолент, Балаклава, Севастополь",
      "timestamp": "2026-07-18T17:37:55+00:00",
      "channel": "lpr1_treugolnik"
    }
  ],
  "lastPostId": {
    "radarrussiia": 82591,
    "kpszsu": 69068,
    "lpr1_treugolnik": 245591,
    "locatorru": 73175
  },
  "updatedAt": "2026-07-18T17:40:47.794Z"
}