{
  "sightings": [
    {
      "id": "radarrussiia/83644:Ставропольский край",
      "location": "Ставропольский край",
      "locationRu": "Ставропольский край",
      "region": "Ставропольский край",
      "lat": 44.3296534,
      "lon": 42.5612279,
      "geocodeSource": "nominatim",
      "geocodePrecision": "point",
      "matchedName": "в Ставропольский край",
      "threatType": "drone",
      "count": null,
      "heading": null,
      "destination": null,
      "destinationLat": null,
      "destinationLon": null,
      "bearing": null,
      "status": "alert",
      "confidence": 0.55,
      "postId": 83644,
      "postLink": "https://t.me/radarrussiia/83644",
      "postText": "Ставропольский край\nОпасность по БПЛА\n\n❗️Радар по всей России - @radarrussiia\n🌐 Обход белых списков - @Internet_Boost_bot",
      "postDate": "2026-07-24T11:21:14+00:00",
      "summary": "Drone activity (alert) at Ставропольский край",
      "timestamp": "2026-07-24T11:21:14+00:00",
      "channel": "radarrussiia"
    },
    {
      "id": "locatorru/74549:Там",
      "location": "Там",
      "locationRu": "Там",
      "region": "",
      "lat": 52.9019574,
      "lon": 41.3578918,
      "geocodeSource": "nominatim",
      "geocodePrecision": "point",
      "matchedName": "Tambov Oblast",
      "threatType": "drone",
      "count": null,
      "heading": null,
      "destination": null,
      "destinationLat": null,
      "destinationLon": null,
      "bearing": null,
      "status": "impact",
      "confidence": 0.55,
      "postId": 74549,
      "postLink": "https://t.me/locatorru/74549",
      "postText": "Сбор практически остановился. 100 рублей, умноженные на 2000 тысяч человек - это 200.000 рублей. Сбор можно закрыть за несколько дней только с сплотиться и объединить всем нам, наши братья, сестра, матеря и отцы!\n\nЗа последние полгода, действия киевской власти перешли все границы, они наносят удары по гражданским объектам. Кроме того, их БПЛА оснащены специальными поражающими элементами, выполненн",
      "postDate": "2026-07-24T11:24:05+00:00",
      "summary": "Drone activity (impact) at За последние полгода, Там",
      "timestamp": "2026-07-24T11:24:05+00:00",
      "channel": "locatorru"
    },
    {
      "id": "lpr1_treugolnik/248660:Кача",
      "location": "Кача",
      "locationRu": "Кача",
      "region": "",
      "lat": 44.7556354,
      "lon": 33.7235003,
      "geocodeSource": "nominatim",
      "geocodePrecision": "point",
      "matchedName": "Кача",
      "threatType": "drone",
      "count": null,
      "heading": null,
      "destination": null,
      "destinationLat": null,
      "destinationLon": null,
      "bearing": null,
      "status": "alert",
      "confidence": 0.55,
      "postId": 248660,
      "postLink": "https://t.me/lpr1_treugolnik/248660",
      "postText": "Кача, Бельбек\nСевастополь\nОпасность по БПЛА\nПовторно",
      "postDate": "2026-07-24T11:35:58+00:00",
      "summary": "Drone activity (alert) at Кача, Бельбек, Севастополь",
      "timestamp": "2026-07-24T11:35:58+00:00",
      "channel": "lpr1_treugolnik"
    },
    {
      "id": "lpr1_treugolnik/248660:Бельбек",
      "location": "Бельбек",
      "locationRu": "Бельбек",
      "region": "",
      "lat": 44.6866456,
      "lon": 33.5669965,
      "geocodeSource": "nominatim",
      "geocodePrecision": "point",
      "matchedName": "Sevastopol International Airport",
      "threatType": "drone",
      "count": null,
      "heading": null,
      "destination": null,
      "destinationLat": null,
      "destinationLon": null,
      "bearing": null,
      "status": "alert",
      "confidence": 0.55,
      "postId": 248660,
      "postLink": "https://t.me/lpr1_treugolnik/248660",
      "postText": "Кача, Бельбек\nСевастополь\nОпасность по БПЛА\nПовторно",
      "postDate": "2026-07-24T11:35:58+00:00",
      "summary": "Drone activity (alert) at Кача, Бельбек, Севастополь",
      "timestamp": "2026-07-24T11:35:58+00:00",
      "channel": "lpr1_treugolnik"
    },
    {
      "id": "lpr1_treugolnik/248660:Севастополь",
      "location": "Севастополь",
      "locationRu": "Севастополь",
      "region": "",
      "lat": 44.6166,
      "lon": 33.5254,
      "geocodeSource": "gazetteer",
      "geocodePrecision": "point",
      "matchedName": "Sevastopol",
      "threatType": "drone",
      "count": null,
      "heading": null,
      "destination": null,
      "destinationLat": null,
      "destinationLon": null,
      "bearing": null,
      "status": "alert",
      "confidence": 0.55,
      "postId": 248660,
      "postLink": "https://t.me/lpr1_treugolnik/248660",
      "postText": "Кача, Бельбек\nСевастополь\nОпасность по БПЛА\nПовторно",
      "postDate": "2026-07-24T11:35:58+00:00",
      "summary": "Drone activity (alert) at Кача, Бельбек, Севастополь",
      "timestamp": "2026-07-24T11:35:58+00:00",
      "channel": "lpr1_treugolnik"
    },
    {
      "id": "lpr1_treugolnik/248671:Белгородский район",
      "location": "Белгородский район",
      "locationRu": "Белгородский район",
      "region": "",
      "lat": 50.5227683,
      "lon": 36.3825126,
      "geocodeSource": "nominatim",
      "geocodePrecision": "point",
      "matchedName": "Белгородский муниципальный округ",
      "threatType": "drone",
      "count": null,
      "heading": null,
      "destination": null,
      "destinationLat": null,
      "destinationLon": null,
      "bearing": null,
      "status": "alert",
      "confidence": 0.55,
      "postId": 248671,
      "postLink": "https://t.me/lpr1_treugolnik/248671",
      "postText": "Белгородский район\nТревога по БПЛА сохраняется",
      "postDate": "2026-07-24T12:11:54+00:00",
      "summary": "Drone activity (alert) at Белгородский район",
      "timestamp": "2026-07-24T12:11:54+00:00",
      "channel": "lpr1_treugolnik"
    },
    {
      "id": "lpr1_treugolnik/248672:Керченский полуостров",
      "location": "Керченский полуостров",
      "locationRu": "Керченский полуостров",
      "region": "",
      "lat": 45.241142,
      "lon": 35.976286,
      "geocodeSource": "nominatim",
      "geocodePrecision": "point",
      "matchedName": "Kerch Peninsula",
      "threatType": "drone",
      "count": null,
      "heading": null,
      "destination": null,
      "destinationLat": null,
      "destinationLon": null,
      "bearing": null,
      "status": "alert",
      "confidence": 0.55,
      "postId": 248672,
      "postLink": "https://t.me/lpr1_treugolnik/248672",
      "postText": "Керченский полуостров\nКерчь\nПорт Кавказ и близлежащие\nОпасность по БПЛА",
      "postDate": "2026-07-24T12:15:57+00:00",
      "summary": "Drone activity (alert) at Керченский полуостров, Керчь, Порт Кавказ и близлежащие",
      "timestamp": "2026-07-24T12:15:57+00:00",
      "channel": "lpr1_treugolnik"
    },
    {
      "id": "lpr1_treugolnik/248672:Керчь",
      "location": "Керчь",
      "locationRu": "Керчь",
      "region": "",
      "lat": 45.3563,
      "lon": 36.4675,
      "geocodeSource": "gazetteer",
      "geocodePrecision": "point",
      "matchedName": "Kerch",
      "threatType": "drone",
      "count": null,
      "heading": null,
      "destination": null,
      "destinationLat": null,
      "destinationLon": null,
      "bearing": null,
      "status": "alert",
      "confidence": 0.55,
      "postId": 248672,
      "postLink": "https://t.me/lpr1_treugolnik/248672",
      "postText": "Керченский полуостров\nКерчь\nПорт Кавказ и близлежащие\nОпасность по БПЛА",
      "postDate": "2026-07-24T12:15:57+00:00",
      "summary": "Drone activity (alert) at Керченский полуостров, Керчь, Порт Кавказ и близлежащие",
      "timestamp": "2026-07-24T12:15:57+00:00",
      "channel": "lpr1_treugolnik"
    }
  ],
  "lastPostId": {
    "radarrussiia": 83644,
    "kpszsu": 69952,
    "lpr1_treugolnik": 248673,
    "locatorru": 74550
  },
  "updatedAt": "2026-07-24T12:17:11.358Z"
}